rvzr/__init__.py
rvzr/analyser.py
rvzr/asm_parser.py
rvzr/cli.py
rvzr/code_generator.py
rvzr/config.py
rvzr/data_generator.py
rvzr/elf_parser.py
rvzr/executor.py
rvzr/factory.py
rvzr/fuzzer.py
rvzr/instruction_spec.py
rvzr/isa_spec.py
rvzr/logs.py
rvzr/model.py
rvzr/py.typed
rvzr/sandbox.py
rvzr/stats.py
rvzr/target_desc.py
rvzr/traces.py
rvzr/unicorn.pyi
rvzr/arch/__init__.py
rvzr/arch/arm64/__init__.py
rvzr/arch/arm64/asm_parser.py
rvzr/arch/arm64/config.py
rvzr/arch/arm64/executor.py
rvzr/arch/arm64/fuzzer.py
rvzr/arch/arm64/generator.py
rvzr/arch/arm64/get_spec.py
rvzr/arch/arm64/target_desc.py
rvzr/arch/x86/__init__.py
rvzr/arch/x86/asm_parser.py
rvzr/arch/x86/config.py
rvzr/arch/x86/executor.py
rvzr/arch/x86/fuzzer.py
rvzr/arch/x86/generator.py
rvzr/arch/x86/get_spec.py
rvzr/arch/x86/target_desc.py
rvzr/model_dynamorio/Makefile
rvzr/model_dynamorio/__init__.py
rvzr/model_dynamorio/model.py
rvzr/model_dynamorio/trace_decoder.py
rvzr/model_dynamorio/adapter/.clang-format
rvzr/model_dynamorio/adapter/.clang-tidy
rvzr/model_dynamorio/adapter/CMakeLists.txt
rvzr/model_dynamorio/adapter/main.c
rvzr/model_dynamorio/adapter/parser.c
rvzr/model_dynamorio/adapter/parser.h
rvzr/model_dynamorio/adapter/rcbf.h
rvzr/model_dynamorio/adapter/rdbf.h
rvzr/model_dynamorio/adapter/sandbox.c
rvzr/model_dynamorio/adapter/sandbox.h
rvzr/model_dynamorio/adapter/sandbox_const.h
rvzr/model_dynamorio/adapter/test_case_entry.S
rvzr/model_dynamorio/backend/.clang-format
rvzr/model_dynamorio/backend/.clang-tidy
rvzr/model_dynamorio/backend/CMakeLists.txt
rvzr/model_dynamorio/backend/cli.cpp
rvzr/model_dynamorio/backend/dispatcher.cpp
rvzr/model_dynamorio/backend/factory.cpp
rvzr/model_dynamorio/backend/logger.cpp
rvzr/model_dynamorio/backend/model.cpp
rvzr/model_dynamorio/backend/speculator_abc.cpp
rvzr/model_dynamorio/backend/taint_tracker.cpp
rvzr/model_dynamorio/backend/tracer_abc.cpp
rvzr/model_dynamorio/backend/util.cpp
rvzr/model_dynamorio/backend/include/cli.hpp
revizor_fuzzer-2.0.0.dist-info/METADATA
revizor_fuzzer-2.0.0.dist-info/WHEEL
revizor_fuzzer-2.0.0.dist-info/entry_points.txt
revizor_fuzzer-2.0.0.dist-info/licenses/AUTHORS
revizor_fuzzer-2.0.0.dist-info/licenses/LICENSE
revizor_fuzzer-2.0.0.dist-info/RECORD
