Metadata-Version: 2.4
Name: revizor-fuzzer
Version: 2.0.0
Summary: A fuzzer to search for microarchitectural leaks in CPUs
Project-URL: Homepage, https://microsoft.github.io/sca-fuzzer/
Project-URL: Source code, https://github.com/microsoft/sca-fuzzer
Project-URL: Bug Tracker, https://github.com/microsoft/sca-fuzzer/issues
Project-URL: Changelog, https://github.com/microsoft/sca-fuzzer/releases
Maintainer: Oleksii Oleksenko
License-File: AUTHORS
License-File: LICENSE
Classifier: License :: OSI Approved :: MIT License
Classifier: Operating System :: POSIX :: Linux
Classifier: Programming Language :: Python :: 3
Classifier: Programming Language :: Python :: 3 :: Only
Classifier: Typing :: Typed
Requires-Python: >=3.9
Requires-Dist: cffi
Requires-Dist: flake8
Requires-Dist: mypy
Requires-Dist: numpy
Requires-Dist: pyelftools
Requires-Dist: pylint
Requires-Dist: pyyaml
Requires-Dist: scipy
Requires-Dist: setuptools<80
Requires-Dist: types-cffi
Requires-Dist: types-pyyaml
Requires-Dist: unicorn; platform_machine == 'aarch64'
Requires-Dist: unicorn==1.0.3; platform_machine == 'x86_64'
Requires-Dist: xxhash
